qasdad/__init__.py
qasdad/calcColumn.py
qasdad/constants.py
qasdad/doxmainpage.py
qasdad/equation.py
qasdad/inactive.py
qasdad/main.py
qasdad/plot.py
qasdad/qasdad.py
qasdad/table.py
qasdad/units.py
qasdad-1.0.2.dist-info/DESCRIPTION.rst
qasdad-1.0.2.dist-info/LICENSE.txt
qasdad-1.0.2.dist-info/METADATA
qasdad-1.0.2.dist-info/RECORD
qasdad-1.0.2.dist-info/WHEEL
qasdad-1.0.2.dist-info/metadata.json
qasdad-1.0.2.dist-info/top_level.txt
