Metadata-Version: 2.0
Name: qasdad
Version: 1.0.2
Summary: Environment for the qasdad scripts
Home-page: https://gitlab.com/volkerweissmann/qasdad
Author: Volker Weißmann
Author-email: volker.weissmann@gmx.de
License: UNKNOWN
Platform: UNKNOWN
Classifier: Programming Language :: Python :: 3
Classifier: License :: OSI Approved :: GNU Affero General Public License v3 or later (AGPLv3+)
Classifier: Operating System :: OS Independent
Requires-Dist: latex2sympy
Requires-Dist: matplotlib
Requires-Dist: numpy
Requires-Dist: scipy
Requires-Dist: sympy
